bsrgan
