Metadata-Version: 2.1
Name: bsrgan
Version: 0.1.5
Summary: Packaged version of the BSRGAN repository
Home-page: https://github.com/kadirnar/bsrgan-pip
Author: kadirnar
License: MIT
Keywords: machine-learning,deep-learning,pytorch,vision,image-classification,Image Super-Resolution,gan
Classifier: Development Status :: 5 - Production/Stable
Classifier: Operating System :: OS Independent
Classifier: Intended Audience :: Developers
Classifier: Intended Audience :: Science/Research
Classifier: Programming Language :: Python :: 3
Classifier: Programming Language :: Python :: 3.7
Classifier: Programming Language :: Python :: 3.8
Classifier: Programming Language :: Python :: 3.9
Classifier: Topic :: Software Development :: Libraries
Classifier: Topic :: Software Development :: Libraries :: Python Modules
Classifier: Topic :: Education
Classifier: Topic :: Scientific/Engineering
Classifier: Topic :: Scientific/Engineering :: Artificial Intelligence
Requires-Python: >=3.6
License-File: LICENSE
